{
  "confirmed": [
    {
      "RepName": "Amy Faulk",
      "Address": "16327 Deerfield Ct",
      "City": "King George",
      "State": "VA",
      "PostalCode": 22485,
      "Latitude": 38.255826,
      "Longitude": -77.060398,
      "fullName": "King George, VA"
    },
    {
      "RepName": "Annette Brown",
      "Address": "4601 Riva Ridge Dr",
      "City": "Olive Branch",
      "State": "MS",
      "PostalCode": 38654,
      "Latitude": 34.926459,
      "Longitude": -89.894834,
      "fullName": "Olive Branch, MS"
    },
    {
      "RepName": "Jennifer Matthews",
      "Address": "1570 Lyle Rd",
      "City": "Dandridge",
      "State": "TN",
      "PostalCode": 37725,
      "Latitude": 35.983553,
      "Longitude": -83.553447,
      "fullName": "Dandridge, TN"
    },
    {
      "RepName": "John Orr",
      "Address": "2512 Wildflower Ct NW",
      "City": "Acworth",
      "State": "GA",
      "PostalCode": 30101,
      "Latitude": 34.059871,
      "Longitude": -84.621551,
      "fullName": "Acworth, GA"
    },
    {
      "RepName": "Kristen Jones",
      "Address": "140 Country Club Rd",
      "City": "Darlington",
      "State": "SC",
      "PostalCode": 29532,
      "Latitude": 34.30554,
      "Longitude": -79.850596,
      "fullName": "Darlington, SC"
    },
    {
      "RepName": "Muriel Curry Whitfield",
      "Address": "2629 Broadway; Apt 8",
      "City": "Fort Myers",
      "State": "FL",
      "PostalCode": 33901,
      "Latitude": 26.629212,
      "Longitude": -81.867991,
      "fullName": "Fort Myers, FL"
    },
    {
      "RepName": "Nicholas Salvato",
      "Address": "2665 Cider Dr",
      "City": "Clarksville",
      "State": "TN",
      "PostalCode": 37040,
      "Latitude": 36.588602,
      "Longitude": -87.340173,
      "fullName": "Clarksville, TN"
    },
    {
      "RepName": "Sabrina Hall",
      "Address": "350 Crossing Blvd; Apt 910",
      "City": "Orange Park",
      "State": "FL",
      "PostalCode": 32073,
      "Latitude": 30.184898,
      "Longitude": -81.718468,
      "fullName": "Orange Park, FL"
    },
    {
      "RepName": "Michelle Rogers",
      "Address": "894 Arbour Rd",
      "City": "Sparta",
      "State": "MO",
      "PostalCode": 65753,
      "Latitude": 37.03151272950249,
      "Longitude":  -93.14507570227585,
      "fullName": "Sparta, MO"
    },
    {
      "RepName": "Lisa Walker",
      "Address": "5 Ridge Drive",
      "City": "Granite Falls",
      "State": "NC",
      "PostalCode": 28630,
      "Latitude": 35.80066471529107, 
      "Longitude":  -81.40575845813242,
      "fullName": "Granite Falls, NC"
    },
    {
      "RepName": "Christina Winston",
      "Address": "335 David St",
      "City": "Seguin",
      "State": "TX",
      "PostalCode": 78155,
      "Latitude": 29.560050149236904,  
      "Longitude":  -97.96781517548715,
      "fullName": "Seguin, TX"
    },
    {
      "RepName": "Heather Lilla",
      "Address": "3114 Shady Springs Dr",
      "City": "Louisville",
      "State": "KY",
      "PostalCode": 40299,
      "Latitude": 38.19437433175258,  
      "Longitude":  -85.52321837340602,
      "fullName": "Louisville, KY"
    },
    {
      "RepName": "Michael McAllister",
      "Address": "103 Stonewood Valley Ln",
      "City": "O'Fallon",
      "State": "MO",
      "PostalCode": 63366,
      "Latitude": 38.78723475878982,  
      "Longitude":   -90.71066993105977,
      "fullName": "O'Fallon, MO"
    },
    {
      "RepName": "Brooke Gross",
      "Address": "6255 Flower Hill Rd; Lot 7",
      "City": "Kenly",
      "State": "NC",
      "PostalCode": 63366,
      "Latitude": 35.69127067343579,  
      "Longitude": -78.17927515998541,
      "fullName": "Kenly, NC"
    },
    {
      "RepName": "Gerard White",
      "Address": "125 Kennely Dr",
      "City": "Folsom",
      "State": "CA",
      "PostalCode": 95630,
      "Latitude": 38.660372271385825, 
      "Longitude": -121.13727758688486,
      "fullName": "Folsom, CA"
    },
    {
      "RepName": "Jennifer Hook",
      "Address": "1161 Ivester Ct",
      "City": "Navassa",
      "State": "NC",
      "PostalCode": 28451,
      "Latitude": 34.256772996515224,  
      "Longitude": -78.02255668886075,
      "fullName": "Navassa, NC"
    },
 {
  "RepName": "Melissa Bokoff",
  "Address": "156 Oak St",
  "City": "Willimantic",
  "State": "CT",
  "PostalCode": 06226,
  "Latitude": 41.7202992125903,
  "Longitude": -72.2061479291186,
  "fullName": "Willimantic, CT"
}
    {
      "RepName": "Sami Jo Slater",
      "Address": "2087 Dogwood Trl",
      "City": "Minden",
      "State": "LA",
      "PostalCode": 71055,
      "Latitude": 32.686154,
      "Longitude": -93.252567,
      "fullName": "Minden, LA"
    }
  ],
  "pending": [
    {
      "RepName": null,
      "Address": null,
      "City": "Belle Vernon",
      "State": "PA",
      "PostalCode": null,
      "Latitude": 40.125798,
      "Longitude": -79.839918,
      "Status": "No applicants",
      "fullName": "Belle Vernon, PA"
    },
    {
      "RepName": null,
      "Address": null,
      "City": "Blair",
      "State": "NE",
      "PostalCode": null,
      "Latitude": 41.543582,
      "Longitude": -96.17653,
      "Status": "No applicants",
      "fullName": "Blair, NE"
    },
    {
      "RepName": null,
      "Address": null,
      "City": "Casa Grande",
      "State": "AZ",
      "PostalCode": null,
      "Latitude": 32.929206,
      "Longitude": -111.748016,
      "Status": "No applicants",
      "fullName": "Casa Grande, AZ"
    },
    {
      "RepName": null,
      "Address": null,
      "City": "Centennial",
      "State": "CO",
      "PostalCode": null,
      "Latitude": 39.535938,
      "Longitude": -104.750752,
      "Status": "No applicants",
      "fullName": "Centennial, CO"
    },
    {
      "RepName": null,
      "Address": null,
      "City": "Centerville",
      "State": "UT",
      "PostalCode": null,
      "Latitude": 40.907472,
      "Longitude": -111.880452,
      "Status": "No applicants",
      "fullName": "Centerville, UT"
    },
    {
      "RepName": null,
      "Address": null,
      "City": "Colton",
      "State": "CA",
      "PostalCode": null,
      "Latitude": 34.076203,
      "Longitude": -117.311279,
      "Status": "No applicants",
      "fullName": "Colton, CA"
    },
    {
      "RepName": null,
      "Address": null,
      "City": "Coral Springs",
      "State": "FL",
      "PostalCode": null,
      "Latitude": 26.266611,
      "Longitude": -80.266147,
      "Status": "No applicants",
      "fullName": "Coral Springs, FL"
    },
    {
      "RepName": null,
      "Address": null,
      "City": "Fort Wayne",
      "State": "IN",
      "PostalCode": null,
      "Latitude": 39.833119,
      "Longitude": -84.893586,
      "Status": "No applicants",
      "fullName": "Fort Wayne, IN"
    },
    {
      "RepName": null,
      "Address": null,
      "City": "Houston",
      "State": "TX",
      "PostalCode": null,
      "Latitude": 29.649614,
      "Longitude": -95.22276,
      "Status": "No applicants",
      "fullName": "Houston, TX"
    },
    {
      "RepName": "Richard Santos",
      "Address": "9936 Azalea Bloom Way; Apt 519",
      "City": "Riverview",
      "State": "FL",
      "PostalCode": "33578",
      "Latitude": 27.857024101494158, 
      "Longitude": -82.34146160436217
      "Status": "Pending offer",
      "fullName": "Riverview, FL"
    },
    {
      "RepName": null,
      "Address": null,
      "City": "Lincoln",
      "State": "IL",
      "PostalCode": "62656",
      "Latitude": 40.1484,
      "Longitude": -89.3648,
      "Status": "No applicants",
      "fullName": "Lincoln, IL"
    },
    {
      "RepName": null,
      "Address": null,
      "City": "Mobile",
      "State": "AL",
      "PostalCode": null,
      "Latitude": 30.70784,
      "Longitude": -88.102501,
      "Status": "No applicants",
      "fullName": "Mobile, AL"
    },
    {
      "RepName": null,
      "Address": null,
      "City": "Muskogee",
      "State": "OK",
      "PostalCode": null,
      "Latitude": 35.357944,
      "Longitude": -95.263256,
      "Status": "No applicants",
      "fullName": "Muskogee, OK"
    },
    {
      "RepName": "Jessica Salvage",
      "Address": "9339 Brookhaven Rd",
      "City": "Kimberly",
      "State": "AL",
      "PostalCode": "35091",
      "Latitude": 33.77753828371402, 
      "Longitude": -86.81475553120215
      "Status": "Pending offer",
      "fullName": "Kimberly, AL"
    },
    {
      "RepName": null,
      "Address": null,
      "City": "Parkesburg",
      "State": "PA",
      "PostalCode": null,
      "Latitude": 39.969641,
      "Longitude": -75.912053,
      "Status": "No applicants",
      "fullName": "Parkesburg, PA"
    },
    {
      "RepName": null,
      "Address": null,
      "City": "Plainfield",
      "State": "IN",
      "PostalCode": null,
      "Latitude": 39.70421,
      "Longitude": -86.39944,
      "Status": "No applicants",
      "fullName": "Plainfield, IN"
    },
    {
      "RepName": null,
      "Address": null,
      "City": "Poulsbo",
      "State": "WA",
      "PostalCode": null,
      "Latitude": 47.751046,
      "Longitude": -122.614094,
      "Status": "No applicants",
      "fullName": "Poulsbo, WA"
    },
    {
      "RepName": null,
      "Address": null,
      "City": "Salem",
      "State": "OR",
      "PostalCode": null,
      "Latitude": 44.639302,
      "Longitude": -123.078092,
      "Status": "No applicants",
      "fullName": "Salem, OR"
    },
    {
      "RepName": "Barbara Reich",
      "Address": "374 Adirondack Dr",
      "City": "Farmingville",
      "State": "NY",
      "PostalCode": "11738",
      "Latitude": 40.84130690381657, 
      "Longitude": -73.0265865175036,
      "Status": "Pending offer",
      "fullName": "Farmingville, NY"
    },
    {
      "RepName": null,
      "Address": null,
      "City": "Waterloo",
      "State": "NY",
      "PostalCode": null,
      "Latitude": 43.078624,
      "Longitude": -76.874457,
      "Status": "No applicants",
      "fullName": "Waterloo, NY"
    },
    {
      "RepName": null,
      "Address": null,
      "City": "White Lake",
      "State": "MI",
      "PostalCode": null,
      "Latitude": 42.692742,
      "Longitude": -83.526847,
      "Status": "No applicants",
      "fullName": "White Lake, MI"
    },
    {
      "RepName": null,
      "Address": null,
      "City": "Williamsburg",
      "State": "VA",
      "PostalCode": null,
      "Latitude": 37.266324,
      "Longitude": -76.700676,
      "Status": "No applicants",
      "fullName": "Williamsburg, VA"
    },
    {
      "RepName": null,
      "Address": null,
      "City": "Wilmington",
      "State": "OH",
      "PostalCode": null,
      "Latitude": 39.442031,
      "Longitude": -83.997012,
      "Status": "No applicants",
      "fullName": "Wilmington, OH"
    },
    {
      "RepName": "Bobby Miller",
      "Address": "710 Big Rock St",
      "City": "Canton",
      "State": "TX",
      "PostalCode": "75103",
      "Latitude": 32.551528,
      "Longitude": -95.867935,
      "Status": "Pending offer",
      "fullName": "Canton, TX"
    },
   {
      "RepName": "Miguel Gonzalez",
      "Address": "35040 N Wilson Rd",
      "City": "Ingleside",
      "State": "IL",
      "PostalCode": "60041",
      "Latitude": 42.37272,
      "Longitude": -88.140338,
      "Status": "Pending offer",
      "fullName": "Ingleside, IL"
    },
    {
      "RepName": null,
      "Address": null,
      "City": "Roseville",
      "State": "MN",
      "PostalCode": null,
      "Latitude": 45.0061, 
      "Longitude": 93.1566,
      "Status": "Pending offer",
      "fullName": "Roseville, MN"
    },
    {
      "RepName": "Sherry Hamrick",
      "Address": "1531 W 9th Street",
      "City": "Ashtabula",
      "State": "OH",
      "PostalCode": "44004",
      "Latitude": 41.894032,
      "Longitude": -80.803107,
      "Status": "Pending offer",
      "fullName": "Ashtabula, OH"
    },
    {
      "RepName": "Angela Eslick",
      "Address": "10300 Aston St",
      "City": "Mabelvale",
      "State": "AR",
      "PostalCode": "72103",
      "Latitude": 34.654717,
      "Longitude": -92.383594,
      "Status": "Pending offer",
      "fullName": "Mabelvale, AR"
    },
    {
      "RepName": "Teryl Ard",
      "Address": "108 Willoway Dr",
      "City": "Norman",
      "State": "OK",
      "PostalCode": "73072",
      "Latitude": 35.217483,
      "Longitude": -97.504106,
      "Status": "Pending offer",
      "fullName": "Norman, OK"
    },
    {
      "RepName": "Justin Vargas Salgado",
      "Address": "1205 Dalbigne St",
      "City": "Belvidere",
      "State": "IL",
      "PostalCode": "61008",
      "Latitude": 42.265642,
      "Longitude": -88.855544,
      "Status": "Pending offer",
      "fullName": "Belvidere, IL"
    },
    {
      "RepName": "Marcie Thibodeaux",
      "Address": "5238 Monceaux Rd",
      "City": "Rayne",
      "State": "LA",
      "PostalCode": "73072",
      "Latitude": 30.22355809524741, 
      "Longitude": -92.29081267547127,
      "Status": "Pending offer",
      "fullName": "Rayne, LA"
    },
    {
      "RepName": "Teresa Estep",
      "Address": "32675 W 146th St",
      "City": "Excelsior Springs",
      "State": "MO",
      "PostalCode": "64024",
      "Latitude": 39.355255,
      "Longitude": -94.1671,
      "Status": "Pending offer",
      "fullName": "Excelsior Springs, MO"
    }
  ]
}
